{
    "enabled": true,
    "models": {
        "face": {
            "name": "control_v11p_sd15_face",
            "module": "none",
            "weight": 0.8,
            "resize_mode": "Resize and Fill",
            "low_vram": false,
            "processor_res": 768,
            "threshold_a": 64,
            "threshold_b": 64,
            "guidance_start": 0.0,
            "guidance_end": 1.0,
            "control_mode": "Balanced",
            "pixel_perfect": true,
            "guessmode": false
        },
        "openpose": {
            "name": "control_v11p_sd15_openpose",
            "module": "openpose",
            "weight": 1.0,
            "resize_mode": "Resize and Fill",
            "low_vram": false,
            "processor_res": 512,
            "threshold_a": 64,
            "threshold_b": 64,
            "guidance_start": 0.0,
            "guidance_end": 1.0,
            "control_mode": "Balanced",
            "pixel_perfect": true,
            "guessmode": false
        },
        "canny": {
            "name": "control_v11p_sd15_canny",
            "module": "canny",
            "weight": 1.0,
            "resize_mode": "Resize and Fill",
            "low_vram": false,
            "processor_res": 512,
            "threshold_a": 100,
            "threshold_b": 200,
            "guidance_start": 0.0,
            "guidance_end": 1.0,
            "control_mode": "Balanced",
            "pixel_perfect": true,
            "guessmode": false
        }
    }
} 